flask_DDoSify/__init__.py
flask_DDoSify/ddosify.py
flask_DDoSify/tools.py
flask_DDoSify/data/Comic_Sans_MS.ttf
flask_DDoSify/data/DroidSansMono.ttf
flask_DDoSify/data/Helvetica.ttf
flask_DDoSify/data/emojis.json
flask_DDoSify/data/languages.json
flask_DDoSify/data/teaemojis.json
flask_DDoSify/templates/block.html
flask_DDoSify/templates/captcha.html
flask_DDoSify/templates/change_language.html
flask_DDoSify/templates/rate_limited.html
flask_DDoSify-1.2.5.dist-info/LICENSE
flask_DDoSify-1.2.5.dist-info/METADATA
flask_DDoSify-1.2.5.dist-info/WHEEL
flask_DDoSify-1.2.5.dist-info/top_level.txt
flask_DDoSify-1.2.5.dist-info/RECORD
