Metadata-Version: 2.1
Name: flask-DDoSify
Version: 1.2.5
Summary: Protect against bots and DDoS attacks
Home-page: https://github.com/tn3w/flask_DDoSify
Author: TN3W
Author-email: tn3wA8xxfuVMs2@proton.me
Keywords: flask,Python,Bot,Captcha,DDoS
Classifier: Environment :: Web Environment
Classifier: Development Status :: 5 - Production/Stable
Classifier: Intended Audience :: Developers
Classifier: License :: OSI Approved :: GNU General Public License v3 (GPLv3)
Classifier: Programming Language :: Python
Classifier: Programming Language :: Python :: 3
Classifier: Topic :: Internet :: WWW/HTTP :: Dynamic Content
Classifier: Topic :: Software Development :: Libraries :: Python Modules
License-File: LICENSE
Requires-Dist: cryptography
Requires-Dist: Flask
Requires-Dist: googletrans ==3.1.0a0
Requires-Dist: beautifulsoup4
Requires-Dist: ipaddress
Requires-Dist: Jinja2
Requires-Dist: Pillow
Requires-Dist: requests
Requires-Dist: bs4
Requires-Dist: captcha
